tcsa/__init__.py
tcsa/cli.py
tcsa/config.json
tcsa/data.py
tcsa/data_preparation.py
tcsa/manual.py
tcsa/model.py
tcsa/pipeline.py
tcsa/prequisite.py
tcsa/thresholding.py
tcsa-0.1.6.dist-info/LICENSE
tcsa-0.1.6.dist-info/METADATA
tcsa-0.1.6.dist-info/WHEEL
tcsa-0.1.6.dist-info/entry_points.txt
tcsa-0.1.6.dist-info/top_level.txt
tcsa-0.1.6.dist-info/RECORD
