Metadata-Version: 2.1
Name: tcsa
Version: 0.1.6
Summary: temporalis segmentation pipeline to assess CSA of temporalis muscle
Author: Computational Oncology
Project-URL: Homepage, https://gitlab.com/computational.oncology/temporalis-segmentation-pipeline
Project-URL: Bug Tracker, https://gitlab.com/computational.oncology/temporalis-segmentation-pipeline/-/issues
Classifier: Development Status :: 4 - Beta
Classifier: Programming Language :: Python :: 3
Classifier: License :: OSI Approved :: GNU General Public License v3 (GPLv3)
Classifier: Operating System :: POSIX
Requires-Python: >=3.7
License-File: LICENSE
Requires-Dist: keras (==2.2.4)
Requires-Dist: tensorflow (==1.14.0)
Requires-Dist: segmentation-models (==1.0.1)
Requires-Dist: protobuf (==3.20.1)
Requires-Dist: h5py (==2.10.0)
Requires-Dist: opencv-python
Requires-Dist: Pillow (==9.5.0)
Requires-Dist: matplotlib (==3.5.3)
Requires-Dist: antspyx
Requires-Dist: nibabel
Requires-Dist: intensity-normalization (==2.1.4)
Requires-Dist: scikit-image
Requires-Dist: gdown
Requires-Dist: tqdm
Requires-Dist: simpleitk
Requires-Dist: requests
Requires-Dist: packaging
Requires-Dist: dicom2nifti
